{
  "android-instant": {
    "REMOTE_SERVER_ROOT": "",
    "host": "",
    "pathPattern": "",
    "recordPath": "",
    "scheme": "https",
    "skipRecord": false
  },
  "appBundle": false,
  "baidugame": {
    "REMOTE_SERVER_ROOT": "",
    "appid": "testappid",
    "orientation": "portrait",
    "subContext": ""
  },
  "encryptJs": true,
  "excludeScenes": [],
  "fb-instant-games": {},
  "includeSDKBox": false,
  "inlineSpriteFrames": false,
  "inlineSpriteFrames_native": true,
  "md5Cache": false,
  "mergeStartScene": false,
  "optimizeHotUpdate": false,
  "orientation": {
    "landscapeLeft": true,
    "landscapeRight": true,
    "portrait": false,
    "upsideDown": false
  },
  "packageName": "org.cocos2d.helloworld",
  "qqplay": {
    "REMOTE_SERVER_ROOT": "",
    "orientation": "portrait",
    "zip": false
  },
  "startScene": "67a56ac9-471a-496c-9611-17d5a3ea4e1f",
  "title": "ceed",
  "webOrientation": "auto",
  "wechatgame": {
    "REMOTE_SERVER_ROOT": "",
    "appid": "wx6ac3f5090a6b99c5",
    "orientation": "portrait",
    "separate_engine": false,
    "subContext": ""
  },
  "xxteaKey": "05ce32f1-7e63-40",
  "zipCompressJs": true
}